{"startTime": "now", "elements": [{"id": 0, "heading": "Wait for Group Session", "name": "Session will start soon", "duration": 0, "gifpath": "static/movie/waitnextworkout.mp4", "sound": null}, {"id": 1, "heading": "Introduction to workouts: 40 work, 10 rest, 3 rounds", "name": ["Squat Walk", "Jumping Lunges", "Burpees", "Plank", "Sit Up", "Inner Sole Tap", "Squat and Knee Tap", "Rope Jump", "Frog Squats", "10 High Knee & 3 Tuck Jumps", "Crunches", "Mountain Climber"], "duration": 5, "gifpath": "", "sound": null}, {"id": 2, "heading": "Introduction to workouts", "name": "Squat Walk", "duration": 10, "gifpath": "static/movie/SquatWalk.mp4", "sound": null}, {"id": 3, "heading": "Introduction to workouts", "name": "Jumping Lunges", "duration": 10, "gifpath": "static/movie/PlyoLunges.mp4", "sound": null}, {"id": 4, "heading": "Introduction to workouts", "name": "Burpees", "duration": 10, "gifpath": "static/movie/Burpee.mp4", "sound": null}, {"id": 5, "heading": "Introduction to workouts", "name": "Plank", "duration": 10, "gifpath": "static/movie/Plank.mp4", "sound": null}, {"id": 6, "heading": "Introduction to workouts", "name": "Sit Up", "duration": 10, "gifpath": "static/movie/SitUp.mp4", "sound": null}, {"id": 7, "heading": "Introduction to workouts", "name": "Inner Sole Tap", "duration": 10, "gifpath": "static/movie/InnerSoleTap.mp4", "sound": null}, {"id": 8, "heading": "Introduction to workouts", "name": "Squat and Knee Tap", "duration": 10, "gifpath": "static/movie/SquatKneeTap.mp4", "sound": null}, {"id": 9, "heading": "Introduction to workouts", "name": "Rope Jump", "duration": 10, "gifpath": "static/movie/RopeJump.mp4", "sound": null}, {"id": 10, "heading": "Introduction to workouts", "name": "Frog Squats", "duration": 10, "gifpath": "static/movie/FrogSquat.mp4", "sound": null}, {"id": 11, "heading": "Introduction to workouts", "name": "10 High Knee & 3 Tuck Jumps", "duration": 10, "gifpath": "static/movie/HighKneeTuckJump.mp4", "sound": null}, {"id": 12, "heading": "Introduction to workouts", "name": "Crunches", "duration": 10, "gifpath": "static/movie/Crunches.mp4", "sound": null}, {"id": 13, "heading": "Introduction to workouts", "name": "Mountain Climber", "duration": 10, "gifpath": "static/movie/MountainClimber.mp4", "sound": null}, {"id": 14, "heading": "Get Ready to Warm Up", "name": " Let's go !!!!! ", "duration": 10, "gifpath": "static/movie/getready.mp4", "sound": null}, {"id": 15, "heading": "Warm Up", "name": "Jumping Jacks", "duration": 25, "gifpath": "static/movie/JumpingJack.mp4", "sound": "audiowork"}, {"id": 16, "heading": "Warm Up", "name": "Butt Kicker", "duration": 25, "gifpath": "static/movie/ButtKicker.mp4", "sound": "audiowork"}, {"id": 17, "heading": "Warm Up", "name": "Squat Pulses", "duration": 25, "gifpath": "static/movie/SquatPulses.mp4", "sound": "audiowork"}, {"id": 18, "heading": "Warm Up", "name": "5 Shoulder Circles & Windmill", "duration": 25, "gifpath": "static/movie/ShouldrCircles.mp4", "sound": "audiowork"}, {"id": 19, "heading": "Warm Up", "name": "Burpees", "duration": 25, "gifpath": "static/movie/Burpee.mp4", "sound": "audiowork"}, {"id": 20, "heading": "Get Ready to Work Out", "name": " Let's go !!!!! ", "duration": 5, "gifpath": "static/movie/getready.mp4", "sound": null}, {"id": 21, "heading": "Workout Time", "name": "Squat Walk", "duration": 40, "gifpath": "static/movie/SquatWalk.mp4", "sound": "audiowork"}, {"id": 22, "heading": "Rest", "name": "Up Next: Jumping Lunges", "duration": 10, "gifpath": "static/movie/Rest1.mp4", "sound": "audiorest"}, {"id": 23, "heading": "Workout Time", "name": "Jumping Lunges", "duration": 40, "gifpath": "static/movie/PlyoLunges.mp4", "sound": "audiowork"}, {"id": 24, "heading": "Rest", "name": "Up Next: Burpees", "duration": 10, "gifpath": "static/movie/Rest1.mp4", "sound": "audiorest"}, {"id": 25, "heading": "Workout Time", "name": "Burpees", "duration": 40, "gifpath": "static/movie/Burpee.mp4", "sound": "audiowork"}, {"id": 26, "heading": "Rest", "name": "Up Next: Plank", "duration": 10, "gifpath": "static/movie/Rest1.mp4", "sound": "audiorest"}, {"id": 27, "heading": "Workout Time", "name": "Plank", "duration": 40, "gifpath": "static/movie/Plank.mp4", "sound": "audiowork"}, {"id": 28, "heading": "Rest", "name": "Up Next: Sit Up", "duration": 10, "gifpath": "static/movie/Rest1.mp4", "sound": "audiorest"}, {"id": 29, "heading": "Workout Time", "name": "Sit Up", "duration": 40, "gifpath": "static/movie/SitUp.mp4", "sound": "audiowork"}, {"id": 30, "heading": "Rest", "name": "Up Next: Inner Sole Tap", "duration": 10, "gifpath": "static/movie/Rest1.mp4", "sound": "audiorest"}, {"id": 31, "heading": "Workout Time", "name": "Inner Sole Tap", "duration": 40, "gifpath": "static/movie/InnerSoleTap.mp4", "sound": "audiowork"}, {"id": 32, "heading": "Rest", "name": "Up Next: Squat and Knee Tap", "duration": 10, "gifpath": "static/movie/Rest1.mp4", "sound": "audiorest"}, {"id": 33, "heading": "Workout Time", "name": "Squat and Knee Tap", "duration": 40, "gifpath": "static/movie/SquatKneeTap.mp4", "sound": "audiowork"}, {"id": 34, "heading": "Rest", "name": "Up Next: Rope Jump", "duration": 10, "gifpath": "static/movie/Rest1.mp4", "sound": "audiorest"}, {"id": 35, "heading": "Workout Time", "name": "Rope Jump", "duration": 40, "gifpath": "static/movie/RopeJump.mp4", "sound": "audiowork"}, {"id": 36, "heading": "Rest", "name": "Up Next: Frog Squats", "duration": 10, "gifpath": "static/movie/Rest1.mp4", "sound": "audiorest"}, {"id": 37, "heading": "Workout Time", "name": "Frog Squats", "duration": 40, "gifpath": "static/movie/FrogSquat.mp4", "sound": "audiowork"}, {"id": 38, "heading": "Rest", "name": "Up Next: 10 High Knee & 3 Tuck Jumps", "duration": 10, "gifpath": "static/movie/Rest1.mp4", "sound": "audiorest"}, {"id": 39, "heading": "Workout Time", "name": "10 High Knee & 3 Tuck Jumps", "duration": 40, "gifpath": "static/movie/HighKneeTuckJump.mp4", "sound": "audiowork"}, {"id": 40, "heading": "Rest", "name": "Up Next: Crunches", "duration": 10, "gifpath": "static/movie/Rest1.mp4", "sound": "audiorest"}, {"id": 41, "heading": "Workout Time", "name": "Crunches", "duration": 40, "gifpath": "static/movie/Crunches.mp4", "sound": "audiowork"}, {"id": 42, "heading": "Rest", "name": "Up Next: Mountain Climber", "duration": 10, "gifpath": "static/movie/Rest1.mp4", "sound": "audiorest"}, {"id": 43, "heading": "Workout Time", "name": "Mountain Climber", "duration": 40, "gifpath": "static/movie/MountainClimber.mp4", "sound": "audiowork"}, {"id": 44, "heading": "Water Break", "name": "Up Next: Squat Walk", "duration": 35, "gifpath": "static/movie/WaterRefill.mp4", "sound": "audiorest"}, {"id": 45, "heading": "Workout Time", "name": "Squat Walk", "duration": 40, "gifpath": "static/movie/SquatWalk.mp4", "sound": "audiowork"}, {"id": 46, "heading": "Rest", "name": "Up Next: Jumping Lunges", "duration": 10, "gifpath": "static/movie/Rest1.mp4", "sound": "audiorest"}, {"id": 47, "heading": "Workout Time", "name": "Jumping Lunges", "duration": 40, "gifpath": "static/movie/PlyoLunges.mp4", "sound": "audiowork"}, {"id": 48, "heading": "Rest", "name": "Up Next: Burpees", "duration": 10, "gifpath": "static/movie/Rest1.mp4", "sound": "audiorest"}, {"id": 49, "heading": "Workout Time", "name": "Burpees", "duration": 40, "gifpath": "static/movie/Burpee.mp4", "sound": "audiowork"}, {"id": 50, "heading": "Rest", "name": "Up Next: Plank", "duration": 10, "gifpath": "static/movie/Rest1.mp4", "sound": "audiorest"}, {"id": 51, "heading": "Workout Time", "name": "Plank", "duration": 40, "gifpath": "static/movie/Plank.mp4", "sound": "audiowork"}, {"id": 52, "heading": "Rest", "name": "Up Next: Sit Up", "duration": 10, "gifpath": "static/movie/Rest1.mp4", "sound": "audiorest"}, {"id": 53, "heading": "Workout Time", "name": "Sit Up", "duration": 40, "gifpath": "static/movie/SitUp.mp4", "sound": "audiowork"}, {"id": 54, "heading": "Rest", "name": "Up Next: Inner Sole Tap", "duration": 10, "gifpath": "static/movie/Rest1.mp4", "sound": "audiorest"}, {"id": 55, "heading": "Workout Time", "name": "Inner Sole Tap", "duration": 40, "gifpath": "static/movie/InnerSoleTap.mp4", "sound": "audiowork"}, {"id": 56, "heading": "Rest", "name": "Up Next: Squat and Knee Tap", "duration": 10, "gifpath": "static/movie/Rest1.mp4", "sound": "audiorest"}, {"id": 57, "heading": "Workout Time", "name": "Squat and Knee Tap", "duration": 40, "gifpath": "static/movie/SquatKneeTap.mp4", "sound": "audiowork"}, {"id": 58, "heading": "Rest", "name": "Up Next: Rope Jump", "duration": 10, "gifpath": "static/movie/Rest1.mp4", "sound": "audiorest"}, {"id": 59, "heading": "Workout Time", "name": "Rope Jump", "duration": 40, "gifpath": "static/movie/RopeJump.mp4", "sound": "audiowork"}, {"id": 60, "heading": "Rest", "name": "Up Next: Frog Squats", "duration": 10, "gifpath": "static/movie/Rest1.mp4", "sound": "audiorest"}, {"id": 61, "heading": "Workout Time", "name": "Frog Squats", "duration": 40, "gifpath": "static/movie/FrogSquat.mp4", "sound": "audiowork"}, {"id": 62, "heading": "Rest", "name": "Up Next: 10 High Knee & 3 Tuck Jumps", "duration": 10, "gifpath": "static/movie/Rest1.mp4", "sound": "audiorest"}, {"id": 63, "heading": "Workout Time", "name": "10 High Knee & 3 Tuck Jumps", "duration": 40, "gifpath": "static/movie/HighKneeTuckJump.mp4", "sound": "audiowork"}, {"id": 64, "heading": "Rest", "name": "Up Next: Crunches", "duration": 10, "gifpath": "static/movie/Rest1.mp4", "sound": "audiorest"}, {"id": 65, "heading": "Workout Time", "name": "Crunches", "duration": 40, "gifpath": "static/movie/Crunches.mp4", "sound": "audiowork"}, {"id": 66, "heading": "Rest", "name": "Up Next: Mountain Climber", "duration": 10, "gifpath": "static/movie/Rest1.mp4", "sound": "audiorest"}, {"id": 67, "heading": "Workout Time", "name": "Mountain Climber", "duration": 40, "gifpath": "static/movie/MountainClimber.mp4", "sound": "audiowork"}, {"id": 68, "heading": "Water Break", "name": "Up Next: Squat Walk", "duration": 35, "gifpath": "static/movie/WaterRefill.mp4", "sound": "audiorest"}, {"id": 69, "heading": "Workout Time", "name": "Squat Walk", "duration": 40, "gifpath": "static/movie/SquatWalk.mp4", "sound": "audiowork"}, {"id": 70, "heading": "Rest", "name": "Up Next: Jumping Lunges", "duration": 10, "gifpath": "static/movie/Rest1.mp4", "sound": "audiorest"}, {"id": 71, "heading": "Workout Time", "name": "Jumping Lunges", "duration": 40, "gifpath": "static/movie/PlyoLunges.mp4", "sound": "audiowork"}, {"id": 72, "heading": "Rest", "name": "Up Next: Burpees", "duration": 10, "gifpath": "static/movie/Rest1.mp4", "sound": "audiorest"}, {"id": 73, "heading": "Workout Time", "name": "Burpees", "duration": 40, "gifpath": "static/movie/Burpee.mp4", "sound": "audiowork"}, {"id": 74, "heading": "Rest", "name": "Up Next: Plank", "duration": 10, "gifpath": "static/movie/Rest1.mp4", "sound": "audiorest"}, {"id": 75, "heading": "Workout Time", "name": "Plank", "duration": 40, "gifpath": "static/movie/Plank.mp4", "sound": "audiowork"}, {"id": 76, "heading": "Rest", "name": "Up Next: Sit Up", "duration": 10, "gifpath": "static/movie/Rest1.mp4", "sound": "audiorest"}, {"id": 77, "heading": "Workout Time", "name": "Sit Up", "duration": 40, "gifpath": "static/movie/SitUp.mp4", "sound": "audiowork"}, {"id": 78, "heading": "Rest", "name": "Up Next: Inner Sole Tap", "duration": 10, "gifpath": "static/movie/Rest1.mp4", "sound": "audiorest"}, {"id": 79, "heading": "Workout Time", "name": "Inner Sole Tap", "duration": 40, "gifpath": "static/movie/InnerSoleTap.mp4", "sound": "audiowork"}, {"id": 80, "heading": "Rest", "name": "Up Next: Squat and Knee Tap", "duration": 10, "gifpath": "static/movie/Rest1.mp4", "sound": "audiorest"}, {"id": 81, "heading": "Workout Time", "name": "Squat and Knee Tap", "duration": 40, "gifpath": "static/movie/SquatKneeTap.mp4", "sound": "audiowork"}, {"id": 82, "heading": "Rest", "name": "Up Next: Rope Jump", "duration": 10, "gifpath": "static/movie/Rest1.mp4", "sound": "audiorest"}, {"id": 83, "heading": "Workout Time", "name": "Rope Jump", "duration": 40, "gifpath": "static/movie/RopeJump.mp4", "sound": "audiowork"}, {"id": 84, "heading": "Rest", "name": "Up Next: Frog Squats", "duration": 10, "gifpath": "static/movie/Rest1.mp4", "sound": "audiorest"}, {"id": 85, "heading": "Workout Time", "name": "Frog Squats", "duration": 40, "gifpath": "static/movie/FrogSquat.mp4", "sound": "audiowork"}, {"id": 86, "heading": "Rest", "name": "Up Next: 10 High Knee & 3 Tuck Jumps", "duration": 10, "gifpath": "static/movie/Rest1.mp4", "sound": "audiorest"}, {"id": 87, "heading": "Workout Time", "name": "10 High Knee & 3 Tuck Jumps", "duration": 40, "gifpath": "static/movie/HighKneeTuckJump.mp4", "sound": "audiowork"}, {"id": 88, "heading": "Rest", "name": "Up Next: Crunches", "duration": 10, "gifpath": "static/movie/Rest1.mp4", "sound": "audiorest"}, {"id": 89, "heading": "Workout Time", "name": "Crunches", "duration": 40, "gifpath": "static/movie/Crunches.mp4", "sound": "audiowork"}, {"id": 90, "heading": "Rest", "name": "Up Next: Mountain Climber", "duration": 10, "gifpath": "static/movie/Rest1.mp4", "sound": "audiorest"}, {"id": 91, "heading": "Workout Time", "name": "Mountain Climber", "duration": 40, "gifpath": "static/movie/MountainClimber.mp4", "sound": "audiowork"}]}